odoo/addons/website_sale_product_item_cart_custom_qty/README.rst
odoo/addons/website_sale_product_item_cart_custom_qty/__init__.py
odoo/addons/website_sale_product_item_cart_custom_qty/__manifest__.py
odoo/addons/website_sale_product_item_cart_custom_qty/i18n/es.po
odoo/addons/website_sale_product_item_cart_custom_qty/i18n/it.po
odoo/addons/website_sale_product_item_cart_custom_qty/i18n/website_sale_product_item_cart_custom_qty.pot
odoo/addons/website_sale_product_item_cart_custom_qty/readme/CONFIGURE.md
odoo/addons/website_sale_product_item_cart_custom_qty/readme/CONTRIBUTORS.md
odoo/addons/website_sale_product_item_cart_custom_qty/readme/DESCRIPTION.md
odoo/addons/website_sale_product_item_cart_custom_qty/readme/USAGE.md
odoo/addons/website_sale_product_item_cart_custom_qty/static/description/icon.png
odoo/addons/website_sale_product_item_cart_custom_qty/static/description/index.html
odoo/addons/website_sale_product_item_cart_custom_qty/static/src/js/tour.esm.js
odoo/addons/website_sale_product_item_cart_custom_qty/static/src/scss/add_to_cart.scss
odoo/addons/website_sale_product_item_cart_custom_qty/tests/__init__.py
odoo/addons/website_sale_product_item_cart_custom_qty/tests/test_website_sale_product_item_cart_custom_qty.py
odoo/addons/website_sale_product_item_cart_custom_qty/views/templates.xml
odoo_addon_website_sale_product_item_cart_custom_qty-18.0.1.0.0.2.dist-info/METADATA
odoo_addon_website_sale_product_item_cart_custom_qty-18.0.1.0.0.2.dist-info/WHEEL
odoo_addon_website_sale_product_item_cart_custom_qty-18.0.1.0.0.2.dist-info/top_level.txt
odoo_addon_website_sale_product_item_cart_custom_qty-18.0.1.0.0.2.dist-info/RECORD
